aiohttp_swagger3/__init__.py
aiohttp_swagger3/context.py
aiohttp_swagger3/exceptions.py
aiohttp_swagger3/handlers.py
aiohttp_swagger3/index_templates.py
aiohttp_swagger3/py.typed
aiohttp_swagger3/routes.py
aiohttp_swagger3/string_formats.py
aiohttp_swagger3/swagger.py
aiohttp_swagger3/swagger_docs.py
aiohttp_swagger3/swagger_file.py
aiohttp_swagger3/swagger_info.py
aiohttp_swagger3/swagger_route.py
aiohttp_swagger3/ui_settings.py
aiohttp_swagger3/validators.py
aiohttp_swagger3/rapidoc_ui/LICENSE
aiohttp_swagger3/rapidoc_ui/VERSION
aiohttp_swagger3/rapidoc_ui/fonts.css
aiohttp_swagger3/rapidoc_ui/rapidoc-min.js
aiohttp_swagger3/rapidoc_ui/rapidoc-regular.woff2
aiohttp_swagger3/rapidoc_ui/rapidoc-semi-bold.woff2
aiohttp_swagger3/rapidoc_ui/roboto-mono-bold.woff2
aiohttp_swagger3/rapidoc_ui/roboto-mono-regular.woff2
aiohttp_swagger3/redoc_ui/LICENSE
aiohttp_swagger3/redoc_ui/VERSION
aiohttp_swagger3/redoc_ui/favicon-16x16.png
aiohttp_swagger3/redoc_ui/favicon-32x32.png
aiohttp_swagger3/redoc_ui/favicon.ico
aiohttp_swagger3/redoc_ui/google-fonts.css
aiohttp_swagger3/redoc_ui/redoc.standalone.js
aiohttp_swagger3/redoc_ui/fonts/montserrat/LICENSE
aiohttp_swagger3/redoc_ui/fonts/montserrat/montserrat-v14-cyrillic-ext_vietnamese_latin-ext_latin_cyrillic-300.woff
aiohttp_swagger3/redoc_ui/fonts/montserrat/montserrat-v14-cyrillic-ext_vietnamese_latin-ext_latin_cyrillic-300.woff2
aiohttp_swagger3/redoc_ui/fonts/montserrat/montserrat-v14-cyrillic-ext_vietnamese_latin-ext_latin_cyrillic-700.woff
aiohttp_swagger3/redoc_ui/fonts/montserrat/montserrat-v14-cyrillic-ext_vietnamese_latin-ext_latin_cyrillic-700.woff2
aiohttp_swagger3/redoc_ui/fonts/montserrat/montserrat-v14-cyrillic-ext_vietnamese_latin-ext_latin_cyrillic-regular.woff
aiohttp_swagger3/redoc_ui/fonts/montserrat/montserrat-v14-cyrillic-ext_vietnamese_latin-ext_latin_cyrillic-regular.woff2
aiohttp_swagger3/redoc_ui/fonts/roboto/LICENSE
aiohttp_swagger3-0.9.0.dist-info/LICENSE
aiohttp_swagger3-0.9.0.dist-info/METADATA
aiohttp_swagger3-0.9.0.dist-info/WHEEL
aiohttp_swagger3-0.9.0.dist-info/top_level.txt
aiohttp_swagger3-0.9.0.dist-info/RECORD
