Metadata-Version: 2.1
Name: aiohttp-swagger3
Version: 0.9.0
Summary: validation for aiohttp swagger openAPI 3
Home-page: https://github.com/hh-h/aiohttp-swagger3
Author: Valetov Konstantin
Author-email: forjob@thetrue.name
License: Apache 2
Classifier: License :: OSI Approved :: Apache Software License
Classifier: Intended Audience :: Developers
Classifier: Programming Language :: Python :: 3 :: Only
Classifier: Programming Language :: Python :: 3.8
Classifier: Programming Language :: Python :: 3.9
Classifier: Programming Language :: Python :: 3.10
Classifier: Programming Language :: Python :: 3.11
Classifier: Development Status :: 4 - Beta
Classifier: Operating System :: POSIX
Classifier: Operating System :: MacOS :: MacOS X
Classifier: Framework :: AsyncIO
Classifier: Topic :: Internet :: WWW/HTTP
Requires-Python: >=3.8
License-File: LICENSE
Requires-Dist: aiohttp <3.11.0,>=3.8.0
Requires-Dist: pyyaml >=5.4.0
Requires-Dist: attrs >=19.3.0
Requires-Dist: fastjsonschema <2.20.0,>=2.15.0
Requires-Dist: rfc3339-validator <1.0,>=0.1.4
